async_cache/__init__.py
async_cache/core.py
async_cache/exceptions.py
async_cache/key_utils.py
async_cache/serialization.py
async_cache/adapters/__init__.py
async_cache/adapters/memory.py
async_cache/adapters/redis.py
async_events/__init__.py
async_events/event_manager.py
async_events/sse_client.py
async_task_worker/__init__.py
async_task_worker/api.py
async_task_worker/core.py
async_task_worker/exceptions.py
async_task_worker/executor.py
async_task_worker/futures.py
async_task_worker/pool.py
async_task_worker/queue.py
async_task_worker/registry.py
async_task_worker/status.py
async_task_worker/adapters/__init__.py
async_task_worker/adapters/cache_adapter.py
async_task_worker-0.4.4.dist-info/METADATA
async_task_worker-0.4.4.dist-info/WHEEL
async_task_worker-0.4.4.dist-info/licenses/LICENSE
async_task_worker-0.4.4.dist-info/RECORD
