Metadata-Version: 2.4
Name: async-task-worker
Version: 0.4.4
Summary: Async Test Worker
Project-URL: Homepage, https://github.com/descoped/async-task-worker
Project-URL: Repository, https://github.com/descoped/async-task-worker
Project-URL: Issues, https://github.com/descoped/async-task-worker/issues
Author-email: Ove Ranheim <oranheim@gmail.com>
License-File: LICENSE
Keywords: asyncio,cache,processor,task,worker
Classifier: License :: OSI Approved :: MIT License
Classifier: Operating System :: OS Independent
Classifier: Programming Language :: Python :: 3
Classifier: Programming Language :: Python :: 3.11
Classifier: Programming Language :: Python :: 3.12
Classifier: Programming Language :: Python :: 3.13
Requires-Python: >=3.11
Requires-Dist: msgpack>=1.1.0
Requires-Dist: pydantic>=2.11.5
